sigma/backends/pd_df/__init__.py
sigma/backends/pd_df/pd_df.py
pysigma_backend_pd_df-0.6.0.dist-info/LICENSE
pysigma_backend_pd_df-0.6.0.dist-info/METADATA
pysigma_backend_pd_df-0.6.0.dist-info/WHEEL
pysigma_backend_pd_df-0.6.0.dist-info/RECORD
