Metadata-Version: 2.1
Name: pySigma-backend-pd_df
Version: 0.6.0
Summary: pySigma Pandas DataFrame Python backend
Home-page: https://github.com/blue-playground/pySigma-backend-pd_df
License: LGPL-3.0-only
Author: Shubham Agarwal
Author-email: shubham.ag.452@gmail.com
Requires-Python: >=3.8,<4.0
Classifier: License :: OSI Approved :: GNU Lesser General Public License v3 (LGPLv3)
Classifier: Programming Language :: Python :: 3
Classifier: Programming Language :: Python :: 3.8
Classifier: Programming Language :: Python :: 3.9
Classifier: Programming Language :: Python :: 3.10
Classifier: Programming Language :: Python :: 3.11
Classifier: Programming Language :: Python :: 3.12
Classifier: Programming Language :: Python :: 3.13
Requires-Dist: pysigma (>=0.11.12,<0.12.0)
Requires-Dist: pytest (>=8.3.3,<9.0.0)
Project-URL: Repository, https://github.com/blue-playground/pySigma-backend-pd_df
